comphardware/__init__.py
comphardware/_models.py
comphardware/data.py
comphardware/helpers.py
comphardware/platform_info.py
comphardware/resources/cpu-database.json
comphardware/resources/gpu-database.json
comphardware-0.1.7.dist-info/LICENSE
comphardware-0.1.7.dist-info/METADATA
comphardware-0.1.7.dist-info/WHEEL
comphardware-0.1.7.dist-info/top_level.txt
comphardware-0.1.7.dist-info/RECORD
