Metadata-Version: 2.1
Name: comphardware
Version: 0.1.7
Summary: Library for comparing hardware
Home-page: https://github.com/MultisampledNight/comphardware
Author: MultisampledNight
Author-email: contact@multisamplednight.com
License: Apache-2
Platform: UNKNOWN
Classifier: Development Status :: 4 - Beta
Classifier: Intended Audience :: Developers
Classifier: Programming Language :: Python :: 3
Classifier: Programming Language :: Python :: 3.8
Classifier: Programming Language :: Python :: 3.9
Classifier: Topic :: System :: Hardware
Classifier: License :: OSI Approved :: Apache Software License
Classifier: Operating System :: POSIX :: Linux
Classifier: Operating System :: Microsoft :: Windows
Classifier: Operating System :: MacOS :: MacOS X
Requires-Python: >=3.8
License-File: LICENSE
Requires-Dist: PyOpenGL
Requires-Dist: psutil
Requires-Dist: py-cpuinfo
Requires-Dist: setuptools
